cnl2asp/__init__.py
cnl2asp/cnl2asp.py
cnl2asp/grammar.lark
cnl2asp/ASP_elements/__init__.py
cnl2asp/ASP_elements/asp_aggregate.py
cnl2asp/ASP_elements/asp_atom.py
cnl2asp/ASP_elements/asp_attribute.py
cnl2asp/ASP_elements/asp_conjunction.py
cnl2asp/ASP_elements/asp_element.py
cnl2asp/ASP_elements/asp_encoding.py
cnl2asp/ASP_elements/asp_operation.py
cnl2asp/ASP_elements/asp_program.py
cnl2asp/ASP_elements/asp_rule.py
cnl2asp/ASP_elements/asp_temporal_formula.py
cnl2asp/ASP_elements/solver/__init__.py
cnl2asp/ASP_elements/solver/clingo_result_parser.py
cnl2asp/ASP_elements/solver/clingo_wrapper.py
cnl2asp/ASP_elements/solver/telingo_result_parser.py
cnl2asp/ASP_elements/solver/telingo_wrapper.py
cnl2asp/converter/__init__.py
cnl2asp/converter/asp_converter.py
cnl2asp/converter/cnl2json_converter.py
cnl2asp/converter/converter_interface.py
cnl2asp/exception/__init__.py
cnl2asp/exception/cnl2asp_exceptions.py
cnl2asp/parser/__init__.py
cnl2asp/parser/command.py
cnl2asp/parser/parser.py
cnl2asp/parser/proposition_builder.py
cnl2asp/specification/__init__.py
cnl2asp/specification/aggregate_component.py
cnl2asp/specification/attribute_component.py
cnl2asp/specification/component.py
cnl2asp/specification/constant_component.py
cnl2asp/specification/entity_component.py
cnl2asp/specification/name_component.py
cnl2asp/specification/operation_component.py
cnl2asp/specification/problem.py
cnl2asp/specification/proposition.py
cnl2asp/specification/relation_component.py
cnl2asp/specification/signaturemanager.py
cnl2asp/specification/specification.py
cnl2asp/utility/__init__.py
cnl2asp/utility/utility.py
cnl2asp-1.3.14.dist-info/licenses/LICENSE
cnl2asp-1.3.14.dist-info/METADATA
cnl2asp-1.3.14.dist-info/WHEEL
cnl2asp-1.3.14.dist-info/entry_points.txt
cnl2asp-1.3.14.dist-info/top_level.txt
cnl2asp-1.3.14.dist-info/RECORD
