Metadata-Version: 2.4
Name: cnl2asp
Version: 1.3.14
Summary: A tool for converting a Controlled Natural Language based on English into Answer Set Programming
Home-page: https://github.com/dodaro/cnl2asp/tree/main
Author: Carmine Dodaro
Author-email: carmine.dodaro@unical.it
Maintainer: Simone Caruso
Maintainer-email: simone.caruso@edu.unige.it
License: Apache License
Requires-Python: >=3.10
License-File: LICENSE
Requires-Dist: lark
Requires-Dist: inflect
Requires-Dist: multipledispatch
Dynamic: author
Dynamic: author-email
Dynamic: description
Dynamic: home-page
Dynamic: license
Dynamic: license-file
Dynamic: maintainer
Dynamic: maintainer-email
Dynamic: requires-dist
Dynamic: requires-python
Dynamic: summary
